Metadata-Version: 2.1
Name: mefulu
Version: 0.0.1
Summary: My Package
Author: Zagumennov U.I.
Author-email: your@domain.com
